getRoutersConfig/__init__.py
getRoutersConfig/src/CiscoClass.py
getRoutersConfig/src/HuaweiClass.py
getRoutersConfig/src/RouterClass.py
getRoutersConfig/src/__init__.py
getRoutersConfig/src/main.py
getRoutersConfig/src/tools.py
getRoutersConfig-0.0.7.dist-info/LICENSE
getRoutersConfig-0.0.7.dist-info/METADATA
getRoutersConfig-0.0.7.dist-info/WHEEL
getRoutersConfig-0.0.7.dist-info/top_level.txt
getRoutersConfig-0.0.7.dist-info/RECORD
