Metadata-Version: 2.1
Name: getRoutersConfig
Version: 0.0.7
Summary: get Cisco and Huawei routers configuration as Json
Home-page: https://github.com/DanielRicklin/getRoutersConfig
Author: DanielRicklin
Author-email: ricklin.daniel@outlook.fr
License: MIT
Classifier: License :: OSI Approved :: MIT License
Classifier: Programming Language :: Python :: 3.10
Classifier: Operating System :: OS Independent
Requires-Python: >=3.7
License-File: LICENSE
Requires-Dist: netmiko (>=4.1.2)
Requires-Dist: pysnmp (>=4.4.12)
Provides-Extra: dev
Requires-Dist: twine (>=4.0.2) ; extra == 'dev'
